README.md
setup.py
howard/__init__.py
howard.egg-info/PKG-INFO
howard.egg-info/SOURCES.txt
howard.egg-info/dependency_links.txt
howard.egg-info/requires.txt
howard.egg-info/top_level.txt