Metadata-Version: 2.1
Name: howard
Version: 1.6.0
Summary: Convert dictionaries to dataclasses and back
Home-page: https://github.com/nhumrich/howard
Author: nhumrich
Author-email: 
License: MIT
Platform: UNKNOWN
